setup.py
JupyterHuck/Help.py
JupyterHuck/MyFunctions.py
JupyterHuck/MyGraph.py
JupyterHuck/MyTree.py
JupyterHuck/MyView.py
JupyterHuck/__init__.py
JupyterHuck/test.py
JupyterHuck.egg-info/PKG-INFO
JupyterHuck.egg-info/SOURCES.txt
JupyterHuck.egg-info/dependency_links.txt
JupyterHuck.egg-info/requires.txt
JupyterHuck.egg-info/top_level.txt
test/test_MyFunctions.py