Metadata-Version: 1.1
Name: JupyterHuck
Version: 0.7
Summary: Visualizing data in a tree structure
Home-page: https://github.com/threemeninaboat3247/JupyterHuck
Author: Yuki Arai
Author-email: threemeninaboat3247@gmail.com
License: MIT
Keywords: data browser
Platform: UNKNOWN
Classifier: Programming Language :: Python :: 3.5
Classifier: Intended Audience :: Science/Research
Classifier: License :: OSI Approved :: MIT License
